jupyterlab_autoimport/__init__.py
jupyterlab_autoimport/_version.py
jupyterlab_autoimport/labextension/build_log.json
jupyterlab_autoimport/labextension/install.json
jupyterlab_autoimport/labextension/package.json
jupyterlab_autoimport/labextension/static/lib_index_js.35f95420160244624313.js
jupyterlab_autoimport/labextension/static/lib_index_js.35f95420160244624313.js.map
jupyterlab_autoimport/labextension/static/remoteEntry.0f8a5f49479a667967a0.js
jupyterlab_autoimport/labextension/static/remoteEntry.0f8a5f49479a667967a0.js.map
jupyterlab_autoimport/labextension/static/style.js
jupyterlab_autoimport/labextension/static/style_index_js.695a63aecc982c3a0e6a.js
jupyterlab_autoimport/labextension/static/style_index_js.695a63aecc982c3a0e6a.js.map
jupyterlab_autoimport/labextension/static/vendors-node_modules_css-loader_dist_runtime_api_js-node_modules_css-loader_dist_runtime_cssW-72eba1.ca48d2a8847cd63608ae.js
jupyterlab_autoimport/labextension/static/vendors-node_modules_css-loader_dist_runtime_api_js-node_modules_css-loader_dist_runtime_cssW-72eba1.ca48d2a8847cd63608ae.js.map
jupyterlab_autoimport-0.1.0.data/data/share/jupyter/labextensions/jupyterlab-autoimport/build_log.json
jupyterlab_autoimport-0.1.0.data/data/share/jupyter/labextensions/jupyterlab-autoimport/install.json
jupyterlab_autoimport-0.1.0.data/data/share/jupyter/labextensions/jupyterlab-autoimport/package.json
jupyterlab_autoimport-0.1.0.data/data/share/jupyter/labextensions/jupyterlab-autoimport/static/lib_index_js.35f95420160244624313.js
jupyterlab_autoimport-0.1.0.data/data/share/jupyter/labextensions/jupyterlab-autoimport/static/lib_index_js.35f95420160244624313.js.map
jupyterlab_autoimport-0.1.0.data/data/share/jupyter/labextensions/jupyterlab-autoimport/static/remoteEntry.0f8a5f49479a667967a0.js
jupyterlab_autoimport-0.1.0.data/data/share/jupyter/labextensions/jupyterlab-autoimport/static/remoteEntry.0f8a5f49479a667967a0.js.map
jupyterlab_autoimport-0.1.0.dist-info/LICENSE
jupyterlab_autoimport-0.1.0.dist-info/METADATA
jupyterlab_autoimport-0.1.0.dist-info/WHEEL
jupyterlab_autoimport-0.1.0.dist-info/top_level.txt
jupyterlab_autoimport-0.1.0.dist-info/RECORD
