Metadata-Version: 2.1
Name: jupyterlab-autoimport
Version: 0.1.0
Summary: A JupyterLab extension for adding import statements for packages loaded with `ipython-autoimport`. The list of import statements in the first code cell gets refreshed by pressing Ctrl-K/Cmd-K.
Home-page: https://github.com/mihao/jupyterlab-autoimport
Author: Michał Kosek
Author-email: 
License: BSD-3-Clause
Keywords: Jupyter,JupyterLab,JupyterLab3
Platform: Linux
Platform: Mac OS X
Platform: Windows
Classifier: License :: OSI Approved :: BSD License
Classifier: Programming Language :: Python
Classifier: Programming Language :: Python :: 3
Classifier: Programming Language :: Python :: 3.7
Classifier: Programming Language :: Python :: 3.8
Classifier: Programming Language :: Python :: 3.9
Classifier: Programming Language :: Python :: 3.10
Classifier: Framework :: Jupyter
Classifier: Framework :: Jupyter :: JupyterLab
Classifier: Framework :: Jupyter :: JupyterLab :: 3
Classifier: Framework :: Jupyter :: JupyterLab :: Extensions
Classifier: Framework :: Jupyter :: JupyterLab :: Extensions :: Prebuilt
Requires-Python: >=3.7
License-File: LICENSE
Requires-Dist: ipython-autoimport (>=0.4)
